aimai_search/__init__.py
aimai_search/lib.py
aimai_search-0.1.0.dist-info/WHEEL
aimai_search-0.1.0.dist-info/METADATA
aimai_search-0.1.0.dist-info/RECORD
